chinillaclvm/CHINILLACLVMObject.py
chinillaclvm/EvalError.py
chinillaclvm/SExp.py
chinillaclvm/__init__.py
chinillaclvm/as_python.py
chinillaclvm/casts.py
chinillaclvm/core_ops.py
chinillaclvm/costs.py
chinillaclvm/more_ops.py
chinillaclvm/op_utils.py
chinillaclvm/operators.py
chinillaclvm/run_program.py
chinillaclvm/serialize.py
chinillaclvm/version.py
chinillaclvm-0.9.8.dist-info/LICENSE
chinillaclvm-0.9.8.dist-info/METADATA
chinillaclvm-0.9.8.dist-info/WHEEL
chinillaclvm-0.9.8.dist-info/top_level.txt
chinillaclvm-0.9.8.dist-info/RECORD
