Metadata-Version: 2.1
Name: chinillaclvm
Version: 0.9.8
Summary: [Contract Language | Chinillalisp] Virtual Machine
Home-page: https://github.com/Chinilla/chinillaclvm
Author: Chinilla Network, Inc.
Author-email: hello@chinilla.com
License: https://opensource.org/licenses/Apache-2.0
Project-URL: Bug Reports, https://github.com/Chinilla/chinillaclvm
Project-URL: Source, https://github.com/Chinilla/chinillaclvm
Classifier: Development Status :: 3 - Alpha
Classifier: Programming Language :: Python :: 3
Classifier: Programming Language :: Python :: 3.6
Classifier: Programming Language :: Python :: 3.7
Classifier: License :: OSI Approved :: Apache Software License
Classifier: Topic :: Security :: Cryptography
License-File: LICENSE
Requires-Dist: chinillablspy (>=0.9)
Provides-Extra: dev
Requires-Dist: chinillaclvm-tools (>=0.4.4) ; extra == 'dev'
Requires-Dist: pytest ; extra == 'dev'
